{
  "baseUrl": "https://test.tech2b.cc/",
  "projectId": "wb3trw",
  "ignoreTestFiles": "*.js",
  "pluginsFile": "cypress/plugins/index.js",
  "supportFile": "cypress/support/index.js",
  "integrationFolder": "cypress/integration",
  "screenshotOnRunFailure": true,
  "trashAssetsBeforeRuns": true,
  "video": false,
  "screenshotsFolder": "cypress/screenshots",
  "testFiles": "**/*.feature",
  "failOnStatusCode": false,
  "reporterOptions": {
    "reportDir": "cypress/results",
    "quiet": true,
    "reportTitle": "Form-Builder",
    "overwrite": false,
    "html": false,
    "json": true,
    "chromeWebSecurity": false
}
  }

